lino_xl/__init__.py
lino_xl/lib/__init__.py
lino_xl/lib/accounting/__init__.py
lino_xl/lib/accounting/accounts.py
lino_xl/lib/accounting/choicelists.py
lino_xl/lib/accounting/fields.py
lino_xl/lib/accounting/mixins.py
lino_xl/lib/accounting/models.py
lino_xl/lib/accounting/roles.py
lino_xl/lib/accounting/ui.py
lino_xl/lib/accounting/utils.py
lino_xl/lib/accounting/config/accounting/voucher_base.weasy.html
lino_xl/lib/accounting/config/accounting/Situation/Default.odt
lino_xl/lib/accounting/config/contacts/Partner/payment_reminder.body.html
lino_xl/lib/accounting/config/contacts/Partner/payment_reminder.weasy.html
lino_xl/lib/accounting/fixtures/__init__.py
lino_xl/lib/accounting/fixtures/demo.py
lino_xl/lib/accounting/fixtures/demo_bookings.py
lino_xl/lib/accounting/fixtures/minimal_ledger.py
lino_xl/lib/accounting/fixtures/pcmn_be.py
lino_xl/lib/accounting/fixtures/std.py
lino_xl/lib/accounting/management/__init__.py
lino_xl/lib/accounting/management/commands/__init__.py
lino_xl/lib/accounting/management/commands/reregister.py
lino_xl/lib/addresses/__init__.py
lino_xl/lib/addresses/choicelists.py
lino_xl/lib/addresses/mixins.py
lino_xl/lib/addresses/models.py
lino_xl/lib/addresses/fixtures/__init__.py
lino_xl/lib/addresses/fixtures/demo2.py
lino_xl/lib/agenda/__init__.py
lino_xl/lib/agenda/models.py
lino_xl/lib/agenda/config/cal/Event/base.weasy.html
lino_xl/lib/agenda/config/cal/Event/default.weasy.html
lino_xl/lib/agenda/fixtures/__init__.py
lino_xl/lib/agenda/fixtures/demo2.py
lino_xl/lib/albums/__init__.py
lino_xl/lib/albums/models.py
lino_xl/lib/albums/fixtures/__init__.py
lino_xl/lib/albums/fixtures/demo.py
lino_xl/lib/ana/__init__.py
lino_xl/lib/ana/models.py
lino_xl/lib/ana/fixtures/__init__.py
lino_xl/lib/ana/fixtures/minimal_ledger.py
lino_xl/lib/appypod/__init__.py
lino_xl/lib/appypod/appy_renderer.py
lino_xl/lib/appypod/choicelists.py
lino_xl/lib/appypod/mixins.py
lino_xl/lib/appypod/models.py
lino_xl/lib/appypod/config/Table-portrait.odt
lino_xl-26.1.4.dist-info/METADATA
lino_xl-26.1.4.dist-info/WHEEL
lino_xl-26.1.4.dist-info/licenses/AUTHORS.rst
lino_xl-26.1.4.dist-info/licenses/COPYING
lino_xl-26.1.4.dist-info/RECORD
