Metadata-Version: 2.4
Name: lino-xl
Version: 26.1.4
Summary: The Lino Extensions Library
Project-URL: Homepage, https://www.lino-framework.org
Project-URL: Repository, https://gitlab.com/lino-framework/xl
Author-email: Rumma & Ko Ltd <info@saffre-rumma.net>, Luc Saffre <luc@saffre-rumma.net>
License:                     GNU AFFERO GENERAL PUBLIC LICENSE
License-File: AUTHORS.rst
License-File: COPYING
Keywords: Django,React,customized,framework
Classifier: Development Status :: 5 - Production/Stable
Classifier: Environment :: Web Environment
Classifier: Framework :: Django
Classifier: Intended Audience :: Developers
Classifier: Intended Audience :: System Administrators
Classifier: License :: OSI Approved :: GNU Affero General Public License v3
Classifier: Natural Language :: English
Classifier: Natural Language :: French
Classifier: Natural Language :: German
Classifier: Operating System :: OS Independent
Classifier: Programming Language :: Python
Classifier: Programming Language :: Python :: 3
Classifier: Topic :: Database :: Front-Ends
Classifier: Topic :: Office/Business
Classifier: Topic :: Software Development :: Libraries :: Application Frameworks
Requires-Python: >=3.8
Requires-Dist: commondata
Requires-Dist: lino
Requires-Dist: setuptools<80
Provides-Extra: dev
Requires-Dist: hatch; extra == 'dev'
Requires-Dist: pytest; extra == 'dev'
Requires-Dist: pytest-cov; extra == 'dev'
